edgar_sec/__about__.py
edgar_sec/__init__.py
edgar_sec/clients.py
edgar_sec/helpers.py
edgar_sec/objects.py
edgar_sec/py.typed
edgar_sec-2.0.1.dist-info/LICENSE
edgar_sec-2.0.1.dist-info/METADATA
edgar_sec-2.0.1.dist-info/WHEEL
edgar_sec-2.0.1.dist-info/RECORD
