Metadata-Version: 2.3
Name: edgar-sec
Version: 2.0.1
Summary: A feature-rich python package for interacting with the US Securities and Exchange Commission API: EDGAR
License: AGPL-3.0-or-later
Keywords: edgar,sec,api,finance,reporting,economics,investing,python,data,financial-data,us-securities-and-exchange-commission,cache,financial analysis,economic analysis,data analysis,data science,data visualization,data mining,data wrangling,data cleaning
Author: Nikhil Sunder
Author-email: nsunder724@gmail.com
Requires-Python: >=3.9,<4.0
Classifier: Development Status :: 5 - Production/Stable
Classifier: Intended Audience :: Financial and Insurance Industry
Classifier: License :: OSI Approved :: GNU Affero General Public License v3
Classifier: License :: OSI Approved :: GNU Affero General Public License v3 or later (AGPLv3+)
Classifier: Operating System :: OS Independent
Classifier: Programming Language :: Python :: 3
Classifier: Programming Language :: Python :: 3.9
Classifier: Programming Language :: Python :: 3.10
Classifier: Programming Language :: Python :: 3.11
Classifier: Programming Language :: Python :: 3.12
Classifier: Programming Language :: Python :: 3.13
Classifier: Topic :: Office/Business :: Financial :: Investment
Provides-Extra: types
Requires-Dist: asyncache
Requires-Dist: cachetools
Requires-Dist: httpx
Requires-Dist: tenacity
Project-URL: Documentation, https://nikhilxsunder.github.io/edgar-sec/
Project-URL: Repository, https://github.com/nikhilxsunder/edgar-sec
